issho/__init__.py
issho/cli.py
issho/config.py
issho/helpers.py
issho/issho.py
issho-0.5.1.dist-info/AUTHORS.rst
issho-0.5.1.dist-info/LICENSE
issho-0.5.1.dist-info/METADATA
issho-0.5.1.dist-info/WHEEL
issho-0.5.1.dist-info/entry_points.txt
issho-0.5.1.dist-info/top_level.txt
issho-0.5.1.dist-info/RECORD
