Metadata-Version: 2.1
Name: issho
Version: 0.5.1
Summary: issho allows easy access to simple commands on a remote machine.
Home-page: https://github.com/michaelbilow/issho
Author: Michael Bilow
Author-email: michael.k.bilow@gmail.com
License: MIT license
Keywords: issho,paramiko,keyring,ssh,sftp,python,python-fire,prompt-toolkit,pysftp,sshed,sshtunnel
Platform: UNKNOWN
Classifier: Development Status :: 2 - Pre-Alpha
Classifier: Intended Audience :: Developers
Classifier: License :: OSI Approved :: MIT License
Classifier: Natural Language :: English
Classifier: Programming Language :: Python :: 3
Classifier: Programming Language :: Python :: 3.5
Classifier: Programming Language :: Python :: 3.6
Classifier: Programming Language :: Python :: 3.7
Requires-Dist: sshtunnel (>=0.1.4)
Requires-Dist: keyring (>=18.0.0)
Requires-Dist: paramiko (>=2.5.0)
Requires-Dist: prompt-toolkit (>=1.0.10)
Requires-Dist: toml (>=0.10.0)
Requires-Dist: fire (>=0.1.3)
Requires-Dist: humanize (>=0.5.1)
